{
  "album": "confliction",
  "albumName": "La Cueva de los Tesoros",
  "language": "es",
  "languageName": "Spanish",
  "trackCount": 132,
  "lyricsCount": 66,
  "lyrics": {
    "1": "song_01_cast_out_of_paradise.md",
    "2": "song_02_cave_of_treasures.md",
    "3": "song_03_the_first_darkness.md",
    "4": "song_04_the_serpent's_curse.md",
    "5": "song_05_satan's_disguise.md",
    "6": "song_06_forty_days_of_fasting.md",
    "7": "song_07_the_word_of_god.md",
    "8": "song_08_from_dust_to_glory.md",
    "9": "song_09_the_cherub_at_the_gate.md",
    "10": "song_10_the_bright_nature.md",
    "11": "song_11_the_covenant.md",
    "12": "song_12_the_golden_rods.md",
    "13": "song_13_the_fig_leaves.md",
    "14": "song_14_the_skins_of_beasts.md",
    "15": "song_15_the_tree_of_life.md",
    "16": "song_16_satan_falls_again.md",
    "17": "song_17_the_promise_of_water.md",
    "18": "song_18_the_blood_of_abel.md",
    "19": "song_19_cain's_punishment.md",
    "20": "song_20_seth_the_chosen.md",
    "21": "song_21_the_generations.md",
    "22": "song_22_the_watchers.md",
    "23": "song_23_enoch_walks_with_god.md",
    "24": "song_24_the_days_of_noah.md",
    "25": "song_25_building_the_ark.md",
    "26": "song_26_enter_the_ark.md",
    "27": "song_27_the_flood.md",
    "28": "song_28_the_rainbow_covenant.md",
    "29": "song_29_the_tower_of_babel.md",
    "30": "song_30_abraham_called.md",
    "31": "song_31_the_promised_seed.md",
    "32": "song_32_jacob's_ladder.md",
    "33": "song_33_joseph_the_dreamer.md",
    "34": "song_34_moses_in_the_basket.md",
    "35": "song_35_the_burning_bush.md",
    "36": "song_36_let_my_people_go.md",
    "37": "song_37_the_passover_lamb.md",
    "38": "song_38_crossing_the_red_sea.md",
    "39": "song_39_manna_from_heaven.md",
    "40": "song_40_the_ten_commandments.md",
    "41": "song_41_the_tabernacle.md",
    "42": "song_42_the_bronze_serpent.md",
    "43": "song_43_the_jordan_crossing.md",
    "44": "song_44_the_walls_of_jericho.md",
    "45": "song_45_the_judges_rise.md",
    "46": "song_46_ruth_and_boaz.md",
    "47": "song_47_david_the_shepherd.md",
    "48": "song_48_goliath_falls.md",
    "49": "song_49_the_house_of_david.md",
    "50": "song_50_solomon's_wisdom.md",
    "51": "song_51_elijah_the_prophet.md",
    "52": "song_52_the_still_small_voice.md",
    "53": "song_53_isaiah_sees_the_lord.md",
    "54": "song_54_the_suffering_servant.md",
    "55": "song_55_daniel_in_babylon.md",
    "56": "song_56_the_fiery_furnace.md",
    "57": "song_57_the_prophecy_of_seventy_weeks.md",
    "58": "song_58_the_return_from_exile.md",
    "59": "song_59_the_silence_breaks.md",
    "60": "song_60_a_voice_in_the_wilderness.md",
    "61": "song_61_the_word_made_flesh.md",
    "62": "song_62_born_in_bethlehem.md",
    "63": "song_63_the_lamb_of_god.md",
    "64": "song_64_the_cross.md",
    "65": "song_65_he_is_risen.md",
    "66": "song_66_from_beginning_to_end.md"
  }
}